prefect_yaml/__init__.py
prefect_yaml/cli.py
prefect_yaml/deployment.py
prefect_yaml/flow/__init__.py
prefect_yaml/flow/config.py
prefect_yaml/flow/output.py
prefect_yaml/py.typed
prefect_yaml-2023.0.1.dist-info/LICENSE
prefect_yaml-2023.0.1.dist-info/WHEEL
prefect_yaml-2023.0.1.dist-info/METADATA
prefect_yaml-2023.0.1.dist-info/entry_points.txt
prefect_yaml-2023.0.1.dist-info/RECORD
