Metadata-Version: 2.1
Name: prefect-yaml
Version: 2023.0.1
Summary: Prefect scheduler for YAML configuration
Home-page: https://github.com/factorpricingmodel/prefect-yaml
License: MIT
Author: Factor Pricing Model
Author-email: factor.pricing.model@gmail.com
Requires-Python: >=3.8,<4.0
Classifier: Development Status :: 2 - Pre-Alpha
Classifier: Intended Audience :: Developers
Classifier: License :: OSI Approved :: MIT License
Classifier: Natural Language :: English
Classifier: Operating System :: OS Independent
Classifier: Programming Language :: Python :: 3
Classifier: Programming Language :: Python :: 3.8
Classifier: Programming Language :: Python :: 3.9
Classifier: Programming Language :: Python :: 3.10
Classifier: Programming Language :: Python :: 3.11
Classifier: Topic :: Software Development :: Libraries
Provides-Extra: docs
Requires-Dist: Sphinx (>=5.0,<6.0) ; extra == "docs"
Requires-Dist: click (>=8.1.3,<9.0.0)
Requires-Dist: insipid-sphinx-theme (>=0.3.6,<0.4.0) ; extra == "docs"
Requires-Dist: myst-parser (>=0.18,<0.19) ; extra == "docs"
Requires-Dist: prefect (>=2.7.1,<3.0.0)
Requires-Dist: ruamel-yaml (>=0.17.21,<0.18.0)
Project-URL: Bug Tracker, https://github.com/factorpricingmodel/prefect-yaml/issues
Project-URL: Changelog, https://github.com/factorpricingmodel/prefect-yaml/blob/main/CHANGELOG.md
Project-URL: Documentation, https://prefect-yaml.readthedocs.io
Project-URL: Repository, https://github.com/factorpricingmodel/prefect-yaml
